{
    "node_id": "a63e4d39db37",
    "test_id": "3c77a83d-9e7d-414e-b247-10df8637ad23",
    "report_id": "1471e147-2758-4737-af02-b922dc933626",
    "num_requests": 32,
    "metrics": {
        "mean_latency": 0.015802010893821716,
        "median_latency": 0.013742685317993164,
        "min_latency": 0.006623744964599609,
        "max_latency": 0.06293582916259766
    }
}{
    "node_id": "a63e4d39db37",
    "test_id": "3c77a83d-9e7d-414e-b247-10df8637ad23",
    "report_id": "7c3ca072-51f2-4b8c-b327-38795d09d69a",
    "num_requests": 36,
    "metrics": {
        "mean_latency": 0.014041933748457167,
        "median_latency": 0.013998985290527344,
        "min_latency": 0.010134696960449219,
        "max_latency": 0.020074129104614258
    }
}{
    "node_id": "a63e4d39db37",
    "test_id": "3c77a83d-9e7d-414e-b247-10df8637ad23",
    "report_id": "3029b375-8acd-4b3e-899e-f2e70cadb872",
    "num_requests": 39,
    "metrics": {
        "mean_latency": 0.01309505487099672,
        "median_latency": 0.013250350952148438,
        "min_latency": 0.007858037948608398,
        "max_latency": 0.021019935607910156
    }
}{
    "node_id": "a63e4d39db37",
    "test_id": "3c77a83d-9e7d-414e-b247-10df8637ad23",
    "report_id": "b8be86f0-7d38-455e-8767-0daf2257e66b",
    "num_requests": 33,
    "metrics": {
        "mean_latency": 0.015238581281719786,
        "median_latency": 0.013446569442749023,
        "min_latency": 0.003988027572631836,
        "max_latency": 0.029091835021972656
    }
}{
    "node_id": "a63e4d39db37",
    "test_id": "3c77a83d-9e7d-414e-b247-10df8637ad23",
    "report_id": "1387684a-06e3-4a2d-aa5e-04b7e3bc34cf",
    "num_requests": 40,
    "metrics": {
        "mean_latency": 0.012562698125839234,
        "median_latency": 0.013025999069213867,
        "min_latency": 0.003969430923461914,
        "max_latency": 0.018845081329345703
    }
}{
    "node_id": "a63e4d39db37",
    "test_id": "3c77a83d-9e7d-414e-b247-10df8637ad23",
    "report_id": "e031792d-312a-4a3b-a976-bfdfcae34327",
    "num_requests": 30,
    "metrics": {
        "mean_latency": 0.0168154239654541,
        "median_latency": 0.014368057250976562,
        "min_latency": 0.007869243621826172,
        "max_latency": 0.0842735767364502
    }
}{
    "node_id": "a63e4d39db37",
    "test_id": "3c77a83d-9e7d-414e-b247-10df8637ad23",
    "report_id": "65de337b-54d0-4885-8182-4746bc9c3464",
    "num_requests": 36,
    "metrics": {
        "mean_latency": 0.013941155539618598,
        "median_latency": 0.01352238655090332,
        "min_latency": 0.006310939788818359,
        "max_latency": 0.02625441551208496
    }
}{
    "node_id": "a63e4d39db37",
    "test_id": "3c77a83d-9e7d-414e-b247-10df8637ad23",
    "report_id": "82aee4d0-6d8b-413f-a6c6-5409a9d4b2f1",
    "num_requests": 42,
    "metrics": {
        "mean_latency": 0.012030896686372302,
        "median_latency": 0.011763572692871094,
        "min_latency": 0.007172346115112305,
        "max_latency": 0.018585920333862305
    }
}{
    "node_id": "a63e4d39db37",
    "test_id": "3c77a83d-9e7d-414e-b247-10df8637ad23",
    "report_id": "cfd9bef5-6e37-42dc-b75a-a7aee648c985",
    "num_requests": 38,
    "metrics": {
        "mean_latency": 0.013166854256077817,
        "median_latency": 0.011895418167114258,
        "min_latency": 0.006366252899169922,
        "max_latency": 0.027683496475219727
    }
}{
    "node_id": "a63e4d39db37",
    "test_id": "3c77a83d-9e7d-414e-b247-10df8637ad23",
    "report_id": "9510f7f9-55cd-4f0f-a0f0-9a4d7f634b34",
    "num_requests": 38,
    "metrics": {
        "mean_latency": 0.01323477218025609,
        "median_latency": 0.01236104965209961,
        "min_latency": 0.008218050003051758,
        "max_latency": 0.027686119079589844
    }
}{
    "node_id": "a63e4d39db37",
    "test_id": "3c77a83d-9e7d-414e-b247-10df8637ad23",
    "report_id": "2e245f8f-f677-4492-83bc-8971182e8b59",
    "num_requests": 41,
    "metrics": {
        "mean_latency": 0.012299095712056974,
        "median_latency": 0.011453628540039062,
        "min_latency": 0.007932186126708984,
        "max_latency": 0.02313518524169922
    }
}{
    "node_id": "a63e4d39db37",
    "test_id": "3c77a83d-9e7d-414e-b247-10df8637ad23",
    "report_id": "b541b061-e5d8-4973-a0b5-ce31685bc216",
    "num_requests": 43,
    "metrics": {
        "mean_latency": 0.011950315431106922,
        "median_latency": 0.010819435119628906,
        "min_latency": 0.005658149719238281,
        "max_latency": 0.03326582908630371
    }
}{
    "node_id": "a63e4d39db37",
    "test_id": "3c77a83d-9e7d-414e-b247-10df8637ad23",
    "report_id": "1b50b3ae-d43b-4874-a731-5013dfc2ecb1",
    "num_requests": 42,
    "metrics": {
        "mean_latency": 0.012018362681070963,
        "median_latency": 0.011056661605834961,
        "min_latency": 0.0066297054290771484,
        "max_latency": 0.022662878036499023
    }
}{
    "node_id": "a63e4d39db37",
    "test_id": "3c77a83d-9e7d-414e-b247-10df8637ad23",
    "report_id": "663af120-7c80-4671-aff3-046aae5fe8a9",
    "num_requests": 35,
    "metrics": {
        "mean_latency": 0.014412191935947963,
        "median_latency": 0.012526512145996094,
        "min_latency": 0.005255699157714844,
        "max_latency": 0.02664947509765625
    }
}{
    "node_id": "a63e4d39db37",
    "test_id": "3c77a83d-9e7d-414e-b247-10df8637ad23",
    "report_id": "8bea6280-ef4b-4e97-b759-fa183e50df7a",
    "num_requests": 41,
    "metrics": {
        "mean_latency": 0.012204437721066358,
        "median_latency": 0.011234760284423828,
        "min_latency": 0.007357358932495117,
        "max_latency": 0.02387380599975586
    }
}{
    "node_id": "a63e4d39db37",
    "test_id": "3c77a83d-9e7d-414e-b247-10df8637ad23",
    "report_id": "4e871856-0541-4d03-bda6-ccef01f7c075",
    "num_requests": 47,
    "metrics": {
        "mean_latency": 0.010839284734523042,
        "median_latency": 0.01067972183227539,
        "min_latency": 0.006078243255615234,
        "max_latency": 0.018379688262939453
    }
}{
    "node_id": "a63e4d39db37",
    "test_id": "3c77a83d-9e7d-414e-b247-10df8637ad23",
    "report_id": "b9c07ad0-485d-43af-802d-204c38b12977",
    "num_requests": 37,
    "metrics": {
        "mean_latency": 0.007220403568164722,
        "median_latency": 0.005041837692260742,
        "min_latency": 0.0029282569885253906,
        "max_latency": 0.024314403533935547
    }
}{
    "node_id": "a63e4d39db37",
    "test_id": "32cf365d-de5c-4f3d-b872-a4a28b698448",
    "report_id": "b904c9dc-fe6a-47ea-8c5a-5ada5c83cf65",
    "num_requests": 28,
    "metrics": {
        "mean_latency": 0.014150210789271764,
        "median_latency": 0.014200925827026367,
        "min_latency": 0.006032228469848633,
        "max_latency": 0.02800273895263672
    }
}{
    "node_id": "a63e4d39db37",
    "test_id": "32cf365d-de5c-4f3d-b872-a4a28b698448",
    "report_id": "ee336b68-b9b1-4acf-af70-3d8a01d9c476",
    "num_requests": 33,
    "metrics": {
        "mean_latency": 0.011175914244218306,
        "median_latency": 0.010538339614868164,
        "min_latency": 0.004816770553588867,
        "max_latency": 0.02211594581604004
    }
}{
    "node_id": "a63e4d39db37",
    "test_id": "32cf365d-de5c-4f3d-b872-a4a28b698448",
    "report_id": "0e65a1cb-4bb7-41b0-ba0c-b98980900dd9",
    "num_requests": 33,
    "metrics": {
        "mean_latency": 0.011034401980313387,
        "median_latency": 0.010760784149169922,
        "min_latency": 0.004647493362426758,
        "max_latency": 0.02056574821472168
    }
}{
    "node_id": "a63e4d39db37",
    "test_id": "32cf365d-de5c-4f3d-b872-a4a28b698448",
    "report_id": "e67f6afe-2c3d-4d81-bf80-85cc9c65adc2",
    "num_requests": 33,
    "metrics": {
        "mean_latency": 0.011138569224964489,
        "median_latency": 0.01116180419921875,
        "min_latency": 0.002834320068359375,
        "max_latency": 0.019851207733154297
    }
}{
    "node_id": "a63e4d39db37",
    "test_id": "32cf365d-de5c-4f3d-b872-a4a28b698448",
    "report_id": "0c53da5e-ee6f-41a4-bbb7-cfe6b56d1464",
    "num_requests": 36,
    "metrics": {
        "mean_latency": 0.00997117492887709,
        "median_latency": 0.008888721466064453,
        "min_latency": 0.003100156784057617,
        "max_latency": 0.023636579513549805
    }
}{
    "node_id": "a63e4d39db37",
    "test_id": "32cf365d-de5c-4f3d-b872-a4a28b698448",
    "report_id": "4089bdb7-a09c-4d42-8e15-25ef1fc0750b",
    "num_requests": 37,
    "metrics": {
        "mean_latency": 0.009437316172831767,
        "median_latency": 0.009488105773925781,
        "min_latency": 0.0031936168670654297,
        "max_latency": 0.02016282081604004
    }
}{
    "node_id": "a63e4d39db37",
    "test_id": "32cf365d-de5c-4f3d-b872-a4a28b698448",
    "report_id": "599b8162-c9a8-41f5-a261-0a692506d028",
    "num_requests": 34,
    "metrics": {
        "mean_latency": 0.010434066548066981,
        "median_latency": 0.009644269943237305,
        "min_latency": 0.003393888473510742,
        "max_latency": 0.017986297607421875
    }
}{
    "node_id": "a63e4d39db37",
    "test_id": "32cf365d-de5c-4f3d-b872-a4a28b698448",
    "report_id": "175db236-c724-4125-8e5c-aab61472d395",
    "num_requests": 39,
    "metrics": {
        "mean_latency": 0.008641701478224535,
        "median_latency": 0.0077440738677978516,
        "min_latency": 0.002959728240966797,
        "max_latency": 0.01812434196472168
    }
}{
    "node_id": "a63e4d39db37",
    "test_id": "32cf365d-de5c-4f3d-b872-a4a28b698448",
    "report_id": "aca72f6f-a71c-45f9-a5ed-1475f1d4b07c",
    "num_requests": 40,
    "metrics": {
        "mean_latency": 0.008449435234069824,
        "median_latency": 0.008657455444335938,
        "min_latency": 0.003416299819946289,
        "max_latency": 0.01315760612487793
    }
}{
    "node_id": "a63e4d39db37",
    "test_id": "32cf365d-de5c-4f3d-b872-a4a28b698448",
    "report_id": "12a353cf-ab2c-4d10-a822-444824f12ac0",
    "num_requests": 41,
    "metrics": {
        "mean_latency": 0.00834654598701291,
        "median_latency": 0.008078336715698242,
        "min_latency": 0.002865314483642578,
        "max_latency": 0.02124643325805664
    }
}{
    "node_id": "a63e4d39db37",
    "test_id": "32cf365d-de5c-4f3d-b872-a4a28b698448",
    "report_id": "73334408-44e1-4982-9d57-18957c525dea",
    "num_requests": 39,
    "metrics": {
        "mean_latency": 0.00878755862896259,
        "median_latency": 0.008177042007446289,
        "min_latency": 0.002660989761352539,
        "max_latency": 0.01862335205078125
    }
}{
    "node_id": "a63e4d39db37",
    "test_id": "32cf365d-de5c-4f3d-b872-a4a28b698448",
    "report_id": "5291f453-e6bf-4f89-b7a0-112ad06fc393",
    "num_requests": 41,
    "metrics": {
        "mean_latency": 0.008269123914765149,
        "median_latency": 0.007327556610107422,
        "min_latency": 0.0029463768005371094,
        "max_latency": 0.029435396194458008
    }
}{
    "node_id": "a63e4d39db37",
    "test_id": "32cf365d-de5c-4f3d-b872-a4a28b698448",
    "report_id": "8aebc8d3-0d32-414a-ac90-04abaa907e7a",
    "num_requests": 38,
    "metrics": {
        "mean_latency": 0.009296279204519172,
        "median_latency": 0.008876800537109375,
        "min_latency": 0.0043487548828125,
        "max_latency": 0.015882253646850586
    }
}{
    "node_id": "a63e4d39db37",
    "test_id": "32cf365d-de5c-4f3d-b872-a4a28b698448",
    "report_id": "1ed5079c-08fd-4dee-af90-67525e24fca6",
    "num_requests": 28,
    "metrics": {
        "mean_latency": 0.0074702330998012,
        "median_latency": 0.0063936710357666016,
        "min_latency": 0.0031280517578125,
        "max_latency": 0.020482778549194336
    }
}